{
  "sections": {
    "daf258f3-ee3a-48cc-800f-ad91cd050d23": {
      "type": "image-with-text",
      "blocks": {
        "template--15218150670397__daf258f3-ee3a-48cc-800f-ad91cd050d23-1687180819be51cbef-0": {
          "type": "title",
          "settings": {
            "title_content": "Brand New",
            "title_color": "#EF7E09"
          }
        },
        "template--15218150670397__daf258f3-ee3a-48cc-800f-ad91cd050d23-1687180819be51cbef-1": {
          "type": "heading",
          "settings": {
            "heading": "Sugar-free Syrup",
            "heading_size": "h1"
          }
        },
        "template--15218150670397__daf258f3-ee3a-48cc-800f-ad91cd050d23-1687180819be51cbef-2": {
          "type": "text",
          "settings": {
            "text": "<p>orem ipsum dolor sit amet, consectetur adipiscing edit, sed do eiusmod tempor incididunt<\/p>",
            "text_style": "body"
          }
        },
        "template--15218150670397__daf258f3-ee3a-48cc-800f-ad91cd050d23-1687180819be51cbef-3": {
          "type": "button",
          "settings": {
            "button_label": "Buy Now",
            "button_link": "#product-grid_content",
            "button_background": "#EF7E09"
          }
        }
      },
      "block_order": [
        "template--15218150670397__daf258f3-ee3a-48cc-800f-ad91cd050d23-1687180819be51cbef-0",
        "template--15218150670397__daf258f3-ee3a-48cc-800f-ad91cd050d23-1687180819be51cbef-1",
        "template--15218150670397__daf258f3-ee3a-48cc-800f-ad91cd050d23-1687180819be51cbef-2",
        "template--15218150670397__daf258f3-ee3a-48cc-800f-ad91cd050d23-1687180819be51cbef-3"
      ],
      "custom_css": [
        "@media screen and (max-width: 600px) {.image-with-text_title {display: none; } .image-with-text__media-item {display: none; } .image-with-text__text {display: none; } .button--primary {display: none; } .image-with-text {background-image: url(https:\/\/cdn.shopify.com\/s\/files\/1\/0269\/9254\/1757\/files\/sugar-free_image.png?v=1685489465); background-attachment: fixed; background-size: contain; background-position: center; }}"
      ],
      "settings": {
        "image": "shopify:\/\/shop_images\/sugar-free_image.png",
        "height": "adapt",
        "desktop_image_width": "medium",
        "layout": "image_first",
        "desktop_content_position": "middle",
        "desktop_content_alignment": "left",
        "content_layout": "no-overlap",
        "color_scheme": "background-1",
        "mobile_content_alignment": "center",
        "padding_top": 8,
        "padding_bottom": 12
      }
    },
    "a872a37d-4400-49e5-b641-2a73cea6bb12": {
      "type": "sugar-free-carousel",
      "settings": {
      }
    },
    "product-grid": {
      "type": "main-collection-product-grid",
      "custom_css": [
        "@media screen and (min-width: 750px) {#product-grid_content {transform: scale(0.9); }}"
      ],
      "settings": {
        "products_per_page": 16,
        "columns_desktop": 4,
        "image_ratio": "adapt",
        "show_secondary_image": false,
        "show_vendor": false,
        "show_rating": true,
        "enable_quick_add": false,
        "enable_filtering": true,
        "filter_type": "horizontal",
        "enable_sorting": true,
        "columns_mobile": "2",
        "padding_top": 12,
        "padding_bottom": 16
      }
    },
    "79b8a26e-23df-4aef-b79c-faae34323750": {
      "type": "custom-liquid",
      "settings": {
        "custom_liquid": "<style>\n@media screen and (max-width: 600px) {\n.image-with-text__content image-with-text__content--middle image-with-text__content--desktop-left image-with-text__content--mobile-center image-with-text__content--adapt gradient color-background-1 content-container {\npadding: 15px 0 43px 0;\n    background-color: #faf8fb;\n}\n.image-with-text__heading h1 {\npadding: 0px !important;\n}\n.image-with-text__content>*+* {\n    margin-top: 0;\n}\n.image-with-text.image-with-text--no-overlap.page-width.isolate {\npadding: 10% 0 5% 0;\n}\n.image-with-text__text-item {\nmargin: 17% 0 -3% 0;\n}\n.image-with-text__content  {\n   padding: 0;\n    margin: 2% 0 6% 0;\n}\n\n}\n@media screen and (min-width: 601px) {\n.image-with-text {\n  width: 100%;\n  height: auto;\n  transform: scale(0.7);\n  margin-top: -60px;\n}\n.image-with-text__content {\n  transform: scale(1.4);\n  margin-left: 10%;\n}\n}\n.image-with-text__media img {\nbackground-image:linear-gradient(160deg, rgba(255, 165, 0, 0.8), rgba(255, 165, 0, 0));\n}\n<\/style>",
        "color_scheme": "background-1",
        "padding_top": 0,
        "padding_bottom": 0
      }
    }
  },
  "order": [
    "daf258f3-ee3a-48cc-800f-ad91cd050d23",
    "a872a37d-4400-49e5-b641-2a73cea6bb12",
    "product-grid",
    "79b8a26e-23df-4aef-b79c-faae34323750"
  ]
}